README.rst
setup.py
src/eukalypse_brew/__init__.py
src/eukalypse_brew/brew.py
src/eukalypse_brew/github.py
src/eukalypse_brew.egg-info/PKG-INFO
src/eukalypse_brew.egg-info/SOURCES.txt
src/eukalypse_brew.egg-info/dependency_links.txt
src/eukalypse_brew.egg-info/not-zip-safe
src/eukalypse_brew.egg-info/requires.txt
src/eukalypse_brew.egg-info/top_level.txt