Metadata-Version: 1.1
Name: eukalypse-brew
Version: 0.1
Summary: quick and dirty website testing toolbox
Home-page: https://github.com/kinkerl/eukalypse_brew
Author: Dennis Schwertel
Author-email: s@digitalkultur.net
License: UNKNOWN
Platform: UNKNOWN
Classifier: Development Status :: 4 - Beta
Classifier: Environment :: Web Environment
Classifier: Intended Audience :: Developers
Classifier: Operating System :: OS Independent
Classifier: Programming Language :: Python
